ACEBinf-1.0.1.dist-info/METADATA
ACEBinf-1.0.1.dist-info/RECORD
ACEBinf-1.0.1.dist-info/WHEEL
ACEBinf-1.0.1.dist-info/top_level.txt
acebinf/__init__.py
acebinf/aligner.py
acebinf/cmd_exe.py
acebinf/log.py
acebinf/math_utils.py
acebinf/multiprocess_utils.py
acebinf/pedigree.py
acebinf/vcf_utils.py
