Metadata-Version: 2.1
Name: ACEBinf
Version: 1.0.1
Summary: UNKNOWN
Home-page: https://github.com/ACEnglish/acebinf
Author: ACEnglish
Author-email: acenglish@gmail.com
License: Unlicense
Platform: UNKNOWN
Requires-Dist: pyvcf (>=0.6.8)
